setup.py
dsnd_probability_v2/Binomialdistribution.py
dsnd_probability_v2/Gaussiandistribution.py
dsnd_probability_v2/Generaldistribution.py
dsnd_probability_v2/__init__.py
dsnd_probability_v2.egg-info/PKG-INFO
dsnd_probability_v2.egg-info/SOURCES.txt
dsnd_probability_v2.egg-info/dependency_links.txt
dsnd_probability_v2.egg-info/not-zip-safe
dsnd_probability_v2.egg-info/top_level.txt