Metadata-Version: 1.0
Name: dsnd-probability-v2
Version: 0.1
Summary: Gaussian and Binomial distributions
Home-page: UNKNOWN
Author: Ashvinee
Author-email: ashvineek9@gmail.com
License: UNKNOWN
Platform: UNKNOWN
